tests/__init__.py
tests/test_cleaners.py
tests/test_extractor.py
tests/test_model_loader.py
tests/test_replay_data.py
wotreplay/__init__.py
wotreplay/wotreplay.py
wotreplay/action/__init__.py
wotreplay/action/extract_data_from_replay.py
wotreplay/helper/__init__.py
wotreplay/helper/cleaners.py
wotreplay/helper/extractor.py
wotreplay/helper/validators.py
wotreplay/orm/__init__.py
wotreplay/orm/data_model.py
wotreplay/utils/__init__.py
wotreplay/utils/engine.py
wotreplay/utils/file_handler.py
wotreplay/utils/loader.py
wotreplay-1.0.2.dist-info/LICENSE
wotreplay-1.0.2.dist-info/METADATA
wotreplay-1.0.2.dist-info/WHEEL
wotreplay-1.0.2.dist-info/top_level.txt
wotreplay-1.0.2.dist-info/RECORD
