Metadata-Version: 2.1
Name: wotreplay
Version: 1.0.2
Summary: World of Tanks PC replay data extractor
Home-page: https://github.com/gabriel-oana/wotreplay
Author: Gabriel Oana
Author-email: gabriel.oana91@gmail.com
License: MIT
Classifier: Development Status :: 5 - Production/Stable
Classifier: Programming Language :: Python :: 3
Classifier: License :: OSI Approved :: MIT License
Classifier: Operating System :: OS Independent
Classifier: Topic :: Software Development :: Libraries :: Python Modules
Classifier: Typing :: Typed
Classifier: Programming Language :: Python :: 3.5
Classifier: Programming Language :: Python :: 3.6
Classifier: Programming Language :: Python :: 3.7
Classifier: Programming Language :: Python :: 3.8
Classifier: Programming Language :: Python :: 3.9
Classifier: Programming Language :: Python :: 3.10
License-File: LICENSE
Requires-Dist: sqlalchemy
Requires-Dist: tqdm
